missinglink/__init__.py
missinglink/legit/__init__.py
missinglink/legit/azure_config.py
missinglink/legit/backend_mixin.py
missinglink/legit/connection_mixin.py
missinglink/legit/content_type.py
missinglink/legit/data_sync.py
missinglink/legit/data_volume_config.py
missinglink/legit/download_entity.py
missinglink/legit/file_hash_generator.py
missinglink/legit/gcp_services.py
missinglink/legit/gcs_utils.py
missinglink/legit/index_metadata_info_generator.py
missinglink/legit/local_data_mapping.py
missinglink/legit/metadata_files.py
missinglink/legit/metadata_validator.py
missinglink/legit/path_utils.py
missinglink/legit/progress_bar.py
missinglink/legit/data_volume/__init__.py
missinglink/legit/data_volume/repo.py
missinglink/legit/db/__init__.py
missinglink/legit/db/backend_conection.py
missinglink/legit/db/base_connection.py
missinglink/legit/db_index/__init__.py
missinglink/legit/db_index/backend_db_index.py
missinglink/legit/db_index/base_db_index.py
missinglink/legit/dulwich/__init__.py
missinglink/legit/dulwich/diff_tree.py
missinglink/legit/dulwich/errors.py
missinglink/legit/dulwich/file.py
missinglink/legit/dulwich/index.py
missinglink/legit/dulwich/lru_cache.py
missinglink/legit/dulwich/object_store.py
missinglink/legit/dulwich/objects.py
missinglink/legit/dulwich/pack.py
missinglink/legit/dulwich/refs.py
missinglink/legit/dulwich/repo.py
missinglink/legit/metadata_db/__init__.py
missinglink/legit/metadata_db/backend_metadata.py
missinglink/legit/metadata_db/base_metadata_db.py
missinglink/legit/metadata_db/limit_visitor.py
missinglink/legit/metadata_db/query_results_cache.py
missinglink/legit/metadata_db/query_results_fetcher.py
missinglink/legit/object_store/__init__.py
missinglink/legit/object_store/disk_object_store.py
missinglink/legit/object_store/ml_base_object_store.py
missinglink/legit/object_store/null_storage.py
missinglink/legit/object_store/gcs/__init__.py
missinglink/legit/object_store/gcs/backend_gcs_object_store.py
ml_legit-19.9.8734.dist-info/METADATA
ml_legit-19.9.8734.dist-info/WHEEL
ml_legit-19.9.8734.dist-info/top_level.txt
ml_legit-19.9.8734.dist-info/RECORD
