Metadata-Version: 2.1
Name: ml-legit
Version: 19.9.8734
Summary: Package for Data Management of MissingLink.ai
Home-page: https://missinglink.ai
Author: missinglink.ai
Author-email: support@missinglink.ai
License: Apache
Platform: UNKNOWN
Classifier: Development Status :: 4 - Beta
Classifier: Intended Audience :: Developers
Classifier: License :: OSI Approved :: Apache Software License
Classifier: Programming Language :: Python
Classifier: Programming Language :: Python :: 3
Classifier: Programming Language :: Python :: 2.7
Requires-Dist: requests (~=2.20)
Requires-Dist: puremagic (~=1.3)
Requires-Dist: ply (~=3.11)
Requires-Dist: pyparsing (==2.4.0)
Requires-Dist: tqdm (~=4.28)
Requires-Dist: retrying (~=1.3)
Requires-Dist: humanize (~=0.5)
Requires-Dist: six (~=1.11)
Requires-Dist: google-cloud-core (>=1.0.0)
Requires-Dist: google-cloud-storage (~=1.15)
Requires-Dist: google-auth (~=1.6)
Requires-Dist: boto3 (~=1.9)
Requires-Dist: urllib3 (<1.25,>=1.20)
Requires-Dist: flatten-json (~=0.1)
Requires-Dist: ml-core (>=19.9.3509)
Requires-Dist: azure-storage-blob (~=1.3)
Requires-Dist: msrestazure (~=0.5)
Requires-Dist: azure-mgmt-storage (~=3.1)
Requires-Dist: msgpack (~=0.6)
Requires-Dist: enum34 ; python_version<"3.4"
Requires-Dist: scandir ; python_version<"3.5"
